big_file_cache/BigFileCache.py
big_file_cache/__init__.py
big_file_cache-0.0.2.dist-info/METADATA
big_file_cache-0.0.2.dist-info/WHEEL
big_file_cache-0.0.2.dist-info/top_level.txt
big_file_cache-0.0.2.dist-info/RECORD
